{
  "id": "carbon-carousel-card.carousel-card",
  "type": "CARBON_CAROUSEL_CARD",
  "options": {
    "title": "Red cherry",
    "description": "Red rili shrimp are a visually striking and easy-to-care-for addition to any freshwater aquarium. Their vibrant colors and clear midsection create a stunning contrast, making them a favorite for shrimp enthusiasts who enjoy breeding and maintaining colorful shrimp colonies. In addition to their beauty, they contribute to the overall cleanliness of the tank, helping to control algae and detritus",
    "carouselId": "carbon-carousel-test"
  }
}
